tensorflow_kmaddela/__init__.py
tensorflow_kmaddela/tf.py
tensorflow_kmaddela-0.1.6.dist-info/METADATA
tensorflow_kmaddela-0.1.6.dist-info/WHEEL
tensorflow_kmaddela-0.1.6.dist-info/RECORD
