Metadata-Version: 2.1
Name: tensorflow-kmaddela
Version: 0.1.6
Summary: 
Author: kenny
Author-email: 97374837+kankenny@users.noreply.github.com
Requires-Python: >=3.10,<4.0
Classifier: Programming Language :: Python :: 3
Classifier: Programming Language :: Python :: 3.10
Classifier: Programming Language :: Python :: 3.11
Classifier: Programming Language :: Python :: 3.12
Classifier: Programming Language :: Python :: 3.13
Requires-Dist: numpy (>=2.2.0,<3.0.0)
